{"Data":{"attr":{"Data":[{"arabic":"Null","atr":"Null","color":"#55FFD4"},{"arabic":"لازم","atr":"F.L","color":"#548DD4"},{"arabic":"لازم و متعدي","atr":"F. LM","color":"#AD2323"},{"arabic":"متعدي","atr":"F. M","color":"#575757"},{"arabic":"مبهم","atr":"M","color":"#575757"},{"arabic":"ادات استثناء","atr":"A.ES","color":"#32BD2F"},{"arabic":"ادات تاکيد","atr":"A.TA","color":"#A8017B"},{"arabic":"اسم آلت","atr":"E.AL","color":"#1301B8"},{"arabic":"اسم استفهام","atr":"E.ES","color":"#F4400B"},{"arabic":"اسم اشاره","atr":"E.ESH","color":"#BF9F3E"},{"arabic":"اسم تفضيل","atr":"E.TF","color":"#E11010"},{"arabic":"اسم تفضيل","atr":"E.TF","color":"#A8017B"},{"arabic":"اسم جامد","atr":"E.JA","color":"#548DD4"},{"arabic":"اسم زمان و مکان","atr":"E.ZM","color":"#AD2323"},{"arabic":"اسم شرط","atr":"E.SH","color":"#E11010"},{"arabic":"اسم فاعل","atr":"E.FAL  ","color":"#2D839F"},{"arabic":"اسم فعل","atr":"E.F","color":"#0000FF"},{"arabic":"اسم مفعول","atr":"E.MA","color":"#F4400B"},{"arabic":"جامد غير مصدري","atr":"J.QM","color":"#BF9F3E"},{"arabic":"صفت مشبهه","atr":"E.SM","color":"#A8017B"},{"arabic":"صيغه مبالغه","atr":"E.SMO","color":"#548DD4"},{"arabic":"ضمير متصل","atr":"E.ZT","color":"#445706"},{"arabic":"ضمير منفصل","atr":"E.ZN","color":"#1126C0"},{"arabic":"ظرف","atr":"E.ZR","color":"#8126C0"},{"arabic":"مصدر","atr":"E.MS","color":"#2D839F"},{"arabic":"مصدر ميمي","atr":"E.MM","color":"#32BD2F"},{"arabic":"موصول","atr":"E.MO","color":"#817418"},{"arabic":"مبهم","atr":"M","color":"#1301B8"},{"arabic":"ابتدائيّة","atr":"EB","color":"#F4400B"},{"arabic":"ادات استثناء","atr":"BG","color":"#F4400B"},{"arabic":"ادات حصر","atr":"H.HS","color":"#2AAAFF"},{"arabic":"استفتاحية","atr":"H.ET","color":"#F4400B"},{"arabic":"استفهاميّة","atr":"H.ES","color":"#2AAAFF"},{"arabic":"استينافيّة","atr":"H.EN","color":"#F4400B"},{"arabic":"اضراب","atr":"H.EZ","color":"#7A57BB"},{"arabic":"امتناعيّة","atr":"H.EM","color":"#E11010"},{"arabic":"تحقيقيّة","atr":"H.TH","color":"#F4400B"},{"arabic":"تعريف","atr":"H.TR","color":"#A8017B"},{"arabic":"تعليلية","atr":"H.TL","color":"#D4FF00"},{"arabic":"تفسيريّة","atr":"H.TF","color":"#D4FF00"},{"arabic":"تنبيهيّه","atr":"H.TN","color":"#D4FF00"},{"arabic":"جارّة","atr":"H.JR","color":"#563128"},{"arabic":"جواب شرط","atr":"H.JSH","color":"#2AAAFF"},{"arabic":"حاليّة","atr":"H.HL","color":"#A8017B"},{"arabic":"حرف استقبال","atr":"H.EST","color":"#A8017B"},{"arabic":"حرف جواب","atr":"H.JV","color":"#563128"},{"arabic":"زائدة","atr":"H.ZA","color":"#A8017B"},{"arabic":"زائدة اللصوقيّة","atr":"H.ZAL","color":"#1301B8"},{"arabic":"زائده","atr":"H.ZA","color":"#563128"},{"arabic":"شبيه به ليس","atr":"H.LS","color":"#1301B8"},{"arabic":"شرطيّة","atr":"H.SHR","color":"#2AAAFF"},{"arabic":"شرطية التّأکيدية الـتّفصيلية","atr":"H.SH.T","color":"#1301B8"},{"arabic":"عاطفة","atr":"H.ET","color":"#AD2323"},{"arabic":"فجائيّة","atr":"H.FJ","color":"#FF5500"},{"arabic":"لام امر","atr":"H.AMR","color":"#AD2323"},{"arabic":"مخففه از ثقيلة","atr":"H.MS","color":"#7A57BB"},{"arabic":"مشبهة بالفعل","atr":"H.MF","color":"#FF5500"},{"arabic":"مصدريّةغير زمانيه","atr":"H.MQZ","color":"#AD2323"},{"arabic":"مصدرية","atr":"H.M","color":"#AD2323"},{"arabic":"مصدريه زمانيه","atr":"H.MZ","color":"#FF5500"},{"arabic":"موطئة للقسم","atr":"H.MQS","color":"#AD2323"},{"arabic":"نا فية للجنس","atr":"H.NJ","color":"#7A57BB"},{"arabic":"ناصبة","atr":"H.NS","color":"#FF5500"},{"arabic":"نافية","atr":"H.NF","color":"#548DD4"},{"arabic":"ناهيّة","atr":"H.NH","color":"#548DD4"},{"arabic":"ندا","atr":"H.ND","color":"#FF5500"},{"arabic":"نفي و استقبال","atr":"H.NFS","color":"#548DD4"},{"arabic":"وصليّة","atr":"H.VO","color":"#FF5500"},{"arabic":"مبهم","atr":"M","color":"#548DD4"},{"arabic":"ضمير متصل غائب منصوبي مجروري","atr":"E.ZTGSJ","color":"#AD2552"},{"arabic":"ضمير متصل متكلم","atr":"E.ZTK","color":"#445706"},{"arabic":"ضمير متصل مخاطب منصوبي مجروري","atr":"E.ZTKHSJ","color":"#AD9765"},{"arabic":"ضمير متصل مرفوعي","atr":"E.ZTGF","color":"#7A57BB"},{"arabic":"الف زينت","atr":"H.NON","color":"#AF2200"},{"arabic":"نون عوض رفع","atr":"H.NON1","color":"#130645"},{"arabic":"تاء تانیث","atr":"H.NON2","color":"#FF5500"},{"arabic":"مقدر","atr":"Z.M","color":"#C5C5C5"}],"TotalCount":77,"Id":"0","IsSuccess":true,"Message":"OK","StatusCode":200,"ValidationMessages":null,"Exception":null,"ResponseTime":"2020-12-02T12:15:02.240589Z"},"relationName":{"Data":[{"color":"#83ADE0","name":"فاعل","Id":1},{"color":"#445706","name":"مستثنا","Id":2},{"color":"#70869C","name":"خبر","Id":3},{"color":"#70869C","name":"مفعول به","Id":4},{"color":"#D73535","name":"مجرور","Id":5},{"color":"#6F9FDB","name":"مضاف الیه ","Id":6},{"color":"#495706","name":"حال","Id":7},{"color":"#9A3CD9","name":"نعت","Id":8},{"color":"#6F9FDB","name":"بدل","Id":9},{"color":"#4C5706","name":"تمییز","Id":10},{"color":"#7FAAFF","name":"معطوف","Id":11},{"color":"#D8019C","name":"توکید","Id":12},{"color":"#EF7D21","name":"متعلق","Id":13},{"color":"#505706","name":"اسم","Id":14},{"color":"#97881C","name":"صله","Id":15},{"color":"#525706","name":"مفعول معه","Id":16},{"color":"#83ADE0","name":"نائب فاعل","Id":17},{"color":"#AD2323","name":"عطف بیان","Id":18},{"color":"#D8019C","name":"مفعول مطلق","Id":19},{"color":"#D73535","name":"ظرف","Id":20},{"color":"#70869C","name":"شرط","Id":21},{"color":"#7FAAFF","name":"جواب شرط","Id":22},{"color":"#70869C","name":"مفعول له","Id":23},{"color":"#4C5706","name":"منادا","Id":24},{"color":"#83ADE0","name":"جواب امر","Id":25},{"color":"#D8019C","name":"منصوب به نزع خافض","Id":26},{"color":"#4C5706","name":"جواب ندا","Id":27},{"color":"#83ADE0","name":"جواب قسم","Id":28},{"color":"#4C5706","name":"تعریف","Id":29},{"color":"#D8019C","name":"ضمیر فصل","Id":30},{"color":"#D73535","name":"استثنا","Id":31},{"color":"#EF7D21","name":"زائد","Id":32},{"color":"#7FAAFF","name":"مشتغل عنه","Id":33},{"color":"#4C5706","name":"معطوف بر محل","Id":34},{"color":"#97881C","name":"تأکید","Id":35},{"color":"#7FAAFF","name":"تحقیق","Id":36},{"color":"#7FAAFF","name":"استقبال","Id":37},{"color":"#7FAAFF","name":"استفهام","Id":38},{"color":"#70869C","name":"نفی","Id":39},{"color":"#97881C","name":"نهی","Id":40},{"color":"#83ADE0","name":"حصر","Id":41},{"color":"#83ADE0","name":"جر زائد","Id":42},{"color":"#D8019C","name":"ابتدا","Id":43},{"color":"#445706","name":"تنبیه","Id":44},{"color":"#97881C","name":"حرف جواب","Id":45},{"color":"#445706","name":"سکت","Id":46},{"color":"#70869C","name":"طلب","Id":47},{"color":"#D8019C","name":"استیناف","Id":48},{"color":"#D8019C","name":"تحضیض","Id":49},{"color":"#83ADE0","name":"تفسیر","Id":50},{"color":"#70869C","name":"تفصیل","Id":51},{"color":"#D8019C","name":"جواب","Id":52},{"color":"#445706","name":"اعتراض","Id":53},{"color":"#D8019C","name":"موطئه","Id":54},{"color":"#7FAAFF","name":"عطف","Id":55},{"color":"#70869C","name":"مفاجاة","Id":56},{"color":"#7FAAFF","name":"مخففه","Id":57},{"color":"#D73535","name":"معیه","Id":58},{"color":"#445706","name":"مصدریه","Id":59},{"color":"#D8019C","name":"اشباع","Id":60},{"color":"#70869C","name":"حالیه","Id":61},{"color":"#D8019C","name":"وقایه","Id":62},{"color":"#FF2200","name":"الف زینت","Id":63},{"color":"#130645","name":"نون عوض رفع","Id":64},{"color":"#FF5500","name":"تاء تانیث","Id":65}],"TotalCount":65,"Id":"0","IsSuccess":true,"Message":"OK","StatusCode":200,"ValidationMessages":null,"Exception":null,"ResponseTime":"2020-12-02T12:15:02.240589Z"},"ayeh":{"node":{"Data":[{"atrId":52,"delete":0,"id":62078,"idWord":45596,"nextId":62079,"prevId":null,"Word":"وَ","xml":"<word Seq=\"1\" Slice=\"وَ\" Entry=\"وَ\" Affix=\"هسته\" Pos=\"حرف\" Lemma=\"وَ\" Case=\"مبنی بر فتح\" Kol=\"عاطفه\" Desc=\"\" />","isNewWord":0},{"atrId":3,"delete":0,"id":62079,"idWord":45597,"nextId":126451,"prevId":62078,"Word":"دَخَلَ","xml":"<word Seq=\"1\" Slice=\"دَخَلَ\" Entry=\"دَخَلَ\" Affix=\"هسته\" Pos=\"فعل\" Case=\"مبنی بر فتح\" Categ=\"فَعَلَ یَفْعُلُ\" Gend=\"مذکر\" Num=\"مفرد\" Root=\"دخل\" RootT=\"سالم\" Temp=\"فَعَلَ\" Time=\"ماضی\" TOV=\"1\" Trans=\"متعدی\" Voic=\"معلوم\" />","isNewWord":0},{"atrId":18,"delete":0,"id":62080,"idWord":45598,"nextId":62081,"prevId":126451,"Word":"جَنَّتَ","xml":"<word Seq=\"1\" Slice=\"جَنَّتَ\" Entry=\"جَنَّةَ\" Affix=\"هسته\" Pos=\"اسم\" Case=\"منصوب\" Categ=\"فَعَلَ یَفْعِلُ\" Def=\"معرفه\" Derv=\"\" DervT=\"جامد غیر مصدری\" Gend=\"مؤنث\" Num=\"مفرد\" Root=\"جنن\" RootT=\"مضاعف\" Temp=\"فَعلَةَ\" Varied=\"تهی\" Decl=\"\" />","isNewWord":0},{"atrId":69,"delete":0,"id":62081,"idWord":45598,"nextId":62082,"prevId":62080,"Word":"هُ","xml":"<word Seq=\"2\" Slice=\"هُ\" Entry=\"هُ\" Affix=\"پسوند\" Pos=\"اسم\" Case=\"مبنی بر ضم\" Categ=\"تهی\" Def=\"معرفه\" Derv=\"\" DervT=\"ضمیر متصل منصوبی مجروری\" Gend=\"مذکر\" Num=\"مفرد\" Root=\"تهی\" RootT=\"تهی\" Temp=\"تهی\" Varied=\"تهی\" Decl=\"\" />","isNewWord":0},{"atrId":43,"delete":0,"id":62082,"idWord":45599,"nextId":62083,"prevId":62081,"Word":"وَ","xml":"<word Seq=\"1\" Slice=\"وَ\" Entry=\"وَ\" Affix=\"هسته\" Pos=\"حرف\" Lemma=\"وَ\" Case=\"مبنی بر فتح\" Kol=\"حالیه\" Desc=\"\" />","isNewWord":0},{"atrId":22,"delete":0,"id":62083,"idWord":45600,"nextId":62084,"prevId":62082,"Word":"هُوَ","xml":"<word Seq=\"1\" Entry=\"هُوَ\" Affix=\"هسته\" Pos=\"اسم\" Case=\"مبنی بر فتح\" Categ=\"تهی\" Def=\"معرفه\" Derv=\"\" DervT=\"ضمیر منفصل مرفوعی\" Gend=\"مذکر\" Num=\"مفرد\" Root=\"تهی\" RootT=\"تهی\" Temp=\"تهی\" Varied=\"تهی\" Decl=\"\" Slice=\"هُوَ\" />","isNewWord":0},{"atrId":15,"delete":0,"id":62084,"idWord":45601,"nextId":62085,"prevId":62083,"Word":"ظَالِمٌ","xml":"<word Seq=\"1\" Slice=\"ظَالِمٌ\" Entry=\"ظَالِمٌ\" Affix=\"هسته\" Pos=\"اسم\" Case=\"مرفوع\" Categ=\"فَعَلَ یَفْعِلُ\" Def=\"نکره\" Derv=\"\" DervT=\"اسم فاعل\" Gend=\"مذکر\" Num=\"مفرد\" Root=\"ظلم\" RootT=\"سالم\" Temp=\"فَاعِلٌ\" Varied=\"منصرف\" Decl=\"\" />","isNewWord":0},{"atrId":41,"delete":0,"id":62085,"idWord":45602,"nextId":62086,"prevId":62084,"Word":"لِ","xml":"<word Seq=\"1\" Slice=\"لِ\" Entry=\"لِ\" Affix=\"پیشوند\" Pos=\"حرف\" Case=\"مبنی بر کسر\" Kol=\"جاره\" />","isNewWord":0},{"atrId":18,"delete":0,"id":62086,"idWord":45602,"nextId":62087,"prevId":62085,"Word":"نَفْسِ","xml":"<word Seq=\"2\" Slice=\"نَفْسِ\" Entry=\"نَفْسِ\" Affix=\"هسته\" Pos=\"اسم\" Case=\"مجرور\" Categ=\"ثلاثی مجرد\" Def=\"اضافه\" DervT=\"جامد غیر مصدری\" Gend=\"مؤنث\" Num=\"مفرد\" Root=\"نفس\" RootT=\"سالم\" Temp=\"فَعْلِ\" Varied=\"منصرف\" />","isNewWord":0},{"atrId":69,"delete":0,"id":62087,"idWord":45602,"nextId":62088,"prevId":62086,"Word":"هِ","xml":"<word Seq=\"3\" Slice=\"هِ\" Entry=\"هُ\" Affix=\"پسوند\" Pos=\"اسم\" Case=\"مبنی بر کسر\" Categ=\"تهی\" Def=\"معرفه\" DervT=\"ضمیر متصل منصوبی مجروری\" Gend=\"مذکر\" Num=\"مفرد\" Root=\"تهی\" RootT=\"تهی\" Temp=\"تهی\" Varied=\"تهی\" />","isNewWord":0},{"atrId":3,"delete":0,"id":62088,"idWord":45603,"nextId":126452,"prevId":62087,"Word":"قَالَ","xml":"<word Seq=\"1\" Entry=\"قَالَ\" Affix=\"هسته\" Pos=\"فعل\" Case=\"مبنی بر فتح\" Categ=\"فَعَلَ یَفْعُلُ\" Gend=\"مذکر\" Num=\"مفرد\" Root=\"قول\" RootT=\"اجوف واوی\" Temp=\"فَعَلَ\" Time=\"ماضی\" TOV=\"1\" Trans=\"متعدی\" Voic=\"معلوم\" Slice=\"قَالَ\" />","isNewWord":0},{"atrId":63,"delete":0,"id":62089,"idWord":45604,"nextId":62090,"prevId":126452,"Word":"مَا","xml":"<word Seq=\"1\" Slice=\"مَا\" Entry=\"مَا\" Affix=\"هسته\" Pos=\"حرف\" Case=\"مبنی بر سکون\" Kol=\"نافیه\" />","isNewWord":0},{"atrId":3,"delete":0,"id":62090,"idWord":45605,"nextId":126453,"prevId":62089,"Word":"أَظُنُّ","xml":"<word Seq=\"1\" Slice=\"أَظُنُّ\" Entry=\"أَظُنُّ\" Affix=\"هسته\" Pos=\"فعل\" Case=\"مرفوع\" Categ=\"فَعَلَ یَفْعُلُ\" Gend=\"تهی\" Num=\"مفرد\" Root=\"ظنن\" RootT=\"مضاعف\" Temp=\"أَفْعُلُ\" Time=\"مضارع ساده\" TOV=\"13\" Trans=\"متعدی\" Voic=\"معلوم\" />","isNewWord":0},{"atrId":58,"delete":0,"id":62091,"idWord":45606,"nextId":62092,"prevId":126453,"Word":"أَنْ","xml":"<word Seq=\"1\" Slice=\"أَنْ\" Entry=\"أَنْ\" Affix=\"هسته\" Pos=\"حرف\" Case=\"مبنی بر سکون\" Kol=\"مصدریه\" />","isNewWord":0},{"atrId":1,"delete":0,"id":62092,"idWord":45607,"nextId":62093,"prevId":62091,"Word":"تَبِيدَ","xml":"<word Seq=\"1\" Slice=\"تَبِيدَ\" Entry=\"تَبِیدَ\" Affix=\"هسته\" Pos=\"فعل\" Lemma=\"بُيُود/بَيَاد/بَيْد\" Case=\"منصوب\" Categ=\"ثلاثی مجرد\" Gend=\"مؤنث\" Num=\"مفرد\" Root=\"بید\" RootT=\"اجوف یائی\" Temp=\"تَفْعِلَ\" Time=\"مضارع ساده\" TOV=\"4\" Trans=\"لازم\" Voic=\"معلوم\" Desc=\"\" />","isNewWord":0},{"atrId":9,"delete":0,"id":62093,"idWord":45608,"nextId":62094,"prevId":62092,"Word":"هَذِهِ","xml":"<word Seq=\"1\" Entry=\"هَذِهِ\" Affix=\"هسته\" Pos=\"اسم\" Case=\"مبنی بر کسر\" Categ=\"تهی\" Def=\"معرفه\" Derv=\"\" DervT=\"اسم اشاره\" Gend=\"مؤنث\" Num=\"مفرد\" Root=\"تهی\" RootT=\"تهی\" Temp=\"تهی\" Varied=\"تهی\" Decl=\"\" Slice=\"هَذِهِ\" />","isNewWord":0},{"atrId":23,"delete":0,"id":62094,"idWord":45609,"nextId":null,"prevId":62093,"Word":"أَبَدًا","xml":"<word Seq=\"1\" Slice=\"أَبَدًا\" Entry=\"أَبَدًا\" Affix=\"هسته\" Pos=\"اسم\" Case=\"منصوب\" Categ=\"فَعَلَ یَفْعِلُ\" Def=\"نکره\" DervT=\"ظرف\" Gend=\"مذکر\" Num=\"مفرد\" Root=\"ءبد\" RootT=\"مهموز الفاء\" Temp=\"فَعَلًا\" Varied=\"منصرف\" />","isNewWord":0},{"atrId":76,"delete":0,"id":126451,"idWord":93643,"nextId":62080,"prevId":62079,"Word":"هو","xml":null,"isNewWord":1},{"atrId":76,"delete":0,"id":126452,"idWord":93644,"nextId":62089,"prevId":62088,"Word":"هو","xml":null,"isNewWord":1},{"atrId":76,"delete":0,"id":126453,"idWord":93645,"nextId":62091,"prevId":62090,"Word":"أنا","xml":null,"isNewWord":1}],"TotalCount":20,"Id":"0","IsSuccess":true,"Message":"OK","StatusCode":200,"ValidationMessages":null,"Exception":null,"ResponseTime":"2020-12-02T12:15:02.240589Z"},"edge":{"Data":[{"arrow":"LTR","ayehId":35,"from":62079,"to":62078,"id":154841,"relationId":55,"word1":"دَخَلَ","word2":"وَ","idRun":62079},{"arrow":"LTR","ayehId":35,"from":62080,"to":62079,"id":40635,"relationId":4,"word1":"جَنَّتَ","word2":"دَخَلَ","idRun":62080},{"arrow":"LTR","ayehId":35,"from":62081,"to":62080,"id":40636,"relationId":6,"word1":"هُ","word2":"جَنَّتَ","idRun":62081},{"arrow":"LTR","ayehId":35,"from":62083,"to":62082,"id":154843,"relationId":61,"word1":"هُوَ","word2":"وَ","idRun":62083},{"arrow":"LTR","ayehId":35,"from":62084,"to":62083,"id":40637,"relationId":3,"word1":"ظَالِمٌ","word2":"هُوَ","idRun":62084},{"arrow":"LTR","ayehId":35,"from":62085,"to":62084,"id":40638,"relationId":13,"word1":"لِ","word2":"ظَالِمٌ","idRun":62085},{"arrow":"LTR","ayehId":35,"from":62086,"to":62085,"id":40639,"relationId":5,"word1":"نَفْسِ","word2":"لِ","idRun":62086},{"arrow":"LTR","ayehId":35,"from":62087,"to":62086,"id":40640,"relationId":6,"word1":"هِ","word2":"نَفْسِ","idRun":62087},{"arrow":"LTR","ayehId":35,"from":62089,"to":62088,"id":154844,"relationId":4,"word1":"مَا","word2":"قَالَ","idRun":62089},{"arrow":"LTR","ayehId":35,"from":62090,"to":62089,"id":154847,"relationId":39,"word1":"أَظُنُّ","word2":"مَا","idRun":62090},{"arrow":"LTR","ayehId":35,"from":62091,"to":62090,"id":154848,"relationId":4,"word1":"أَنْ","word2":"أَظُنُّ","idRun":62091},{"arrow":"LTR","ayehId":35,"from":62092,"to":62091,"id":154849,"relationId":59,"word1":"تَبِيدَ","word2":"أَنْ","idRun":62092},{"arrow":"LTR","ayehId":35,"from":62093,"to":62092,"id":40644,"relationId":1,"word1":"هَذِهِ","word2":"تَبِيدَ","idRun":62093},{"arrow":"LTR","ayehId":35,"from":62094,"to":62092,"id":40645,"relationId":20,"word1":"أَبَدًا","word2":"تَبِيدَ","idRun":62094},{"arrow":"LTR","ayehId":35,"from":126451,"to":62082,"id":154842,"relationId":7,"word1":"هو","word2":"وَ","idRun":126451},{"arrow":"LTR","ayehId":35,"from":126451,"to":62079,"id":40634,"relationId":1,"word1":"هو","word2":"دَخَلَ","idRun":126451},{"arrow":"LTR","ayehId":35,"from":126452,"to":62088,"id":40642,"relationId":1,"word1":"هو","word2":"قَالَ","idRun":126452},{"arrow":"LTR","ayehId":35,"from":126453,"to":62090,"id":40643,"relationId":1,"word1":"أنا","word2":"أَظُنُّ","idRun":126453}],"TotalCount":18,"Id":"0","IsSuccess":true,"Message":"OK","StatusCode":200,"ValidationMessages":null,"Exception":null,"ResponseTime":"2020-12-02T12:15:02.240589Z"},"text":[{"Id":2191,"Number":35,"HasProstration":false,"PageNumber":298,"JuzNumber":15,"Text":"وَدَخَلَ جَنَّتَهُۥ وَهُوَ ظَالِمٞ لِّنَفۡسِهِۦ قَالَ مَآ أَظُنُّ أَن تَبِيدَ هَٰذِهِۦٓ أَبَدٗا","SurahTitle":"الكهف","SurahId":18,"FileUrl":"/File/Sound/Recitation/1-AbdeAlrahmaanSudis/sudis018035.mp3","MaxAyahNumber":110,"MaxAyahNumberPrevSurah":111,"ResultCount":1}]}},"Id":null,"IsSuccess":true,"Message":null,"StatusCode":200,"ValidationMessages":null,"Exception":null,"ResponseTime":"2020-12-02T12:15:02.2126151Z"}