{"Data":{"attr":{"Data":[{"arabic":"Null","atr":"Null","color":"#55FFD4"},{"arabic":"لازم","atr":"F.L","color":"#548DD4"},{"arabic":"لازم و متعدي","atr":"F. LM","color":"#AD2323"},{"arabic":"متعدي","atr":"F. M","color":"#575757"},{"arabic":"مبهم","atr":"M","color":"#575757"},{"arabic":"ادات استثناء","atr":"A.ES","color":"#32BD2F"},{"arabic":"ادات تاکيد","atr":"A.TA","color":"#A8017B"},{"arabic":"اسم آلت","atr":"E.AL","color":"#1301B8"},{"arabic":"اسم استفهام","atr":"E.ES","color":"#F4400B"},{"arabic":"اسم اشاره","atr":"E.ESH","color":"#BF9F3E"},{"arabic":"اسم تفضيل","atr":"E.TF","color":"#E11010"},{"arabic":"اسم تفضيل","atr":"E.TF","color":"#A8017B"},{"arabic":"اسم جامد","atr":"E.JA","color":"#548DD4"},{"arabic":"اسم زمان و مکان","atr":"E.ZM","color":"#AD2323"},{"arabic":"اسم شرط","atr":"E.SH","color":"#E11010"},{"arabic":"اسم فاعل","atr":"E.FAL  ","color":"#2D839F"},{"arabic":"اسم فعل","atr":"E.F","color":"#0000FF"},{"arabic":"اسم مفعول","atr":"E.MA","color":"#F4400B"},{"arabic":"جامد غير مصدري","atr":"J.QM","color":"#BF9F3E"},{"arabic":"صفت مشبهه","atr":"E.SM","color":"#A8017B"},{"arabic":"صيغه مبالغه","atr":"E.SMO","color":"#548DD4"},{"arabic":"ضمير متصل","atr":"E.ZT","color":"#445706"},{"arabic":"ضمير منفصل","atr":"E.ZN","color":"#1126C0"},{"arabic":"ظرف","atr":"E.ZR","color":"#8126C0"},{"arabic":"مصدر","atr":"E.MS","color":"#2D839F"},{"arabic":"مصدر ميمي","atr":"E.MM","color":"#32BD2F"},{"arabic":"موصول","atr":"E.MO","color":"#817418"},{"arabic":"مبهم","atr":"M","color":"#1301B8"},{"arabic":"ابتدائيّة","atr":"EB","color":"#F4400B"},{"arabic":"ادات استثناء","atr":"BG","color":"#F4400B"},{"arabic":"ادات حصر","atr":"H.HS","color":"#2AAAFF"},{"arabic":"استفتاحية","atr":"H.ET","color":"#F4400B"},{"arabic":"استفهاميّة","atr":"H.ES","color":"#2AAAFF"},{"arabic":"استينافيّة","atr":"H.EN","color":"#F4400B"},{"arabic":"اضراب","atr":"H.EZ","color":"#7A57BB"},{"arabic":"امتناعيّة","atr":"H.EM","color":"#E11010"},{"arabic":"تحقيقيّة","atr":"H.TH","color":"#F4400B"},{"arabic":"تعريف","atr":"H.TR","color":"#A8017B"},{"arabic":"تعليلية","atr":"H.TL","color":"#D4FF00"},{"arabic":"تفسيريّة","atr":"H.TF","color":"#D4FF00"},{"arabic":"تنبيهيّه","atr":"H.TN","color":"#D4FF00"},{"arabic":"جارّة","atr":"H.JR","color":"#563128"},{"arabic":"جواب شرط","atr":"H.JSH","color":"#2AAAFF"},{"arabic":"حاليّة","atr":"H.HL","color":"#A8017B"},{"arabic":"حرف استقبال","atr":"H.EST","color":"#A8017B"},{"arabic":"حرف جواب","atr":"H.JV","color":"#563128"},{"arabic":"زائدة","atr":"H.ZA","color":"#A8017B"},{"arabic":"زائدة اللصوقيّة","atr":"H.ZAL","color":"#1301B8"},{"arabic":"زائده","atr":"H.ZA","color":"#563128"},{"arabic":"شبيه به ليس","atr":"H.LS","color":"#1301B8"},{"arabic":"شرطيّة","atr":"H.SHR","color":"#2AAAFF"},{"arabic":"شرطية التّأکيدية الـتّفصيلية","atr":"H.SH.T","color":"#1301B8"},{"arabic":"عاطفة","atr":"H.ET","color":"#AD2323"},{"arabic":"فجائيّة","atr":"H.FJ","color":"#FF5500"},{"arabic":"لام امر","atr":"H.AMR","color":"#AD2323"},{"arabic":"مخففه از ثقيلة","atr":"H.MS","color":"#7A57BB"},{"arabic":"مشبهة بالفعل","atr":"H.MF","color":"#FF5500"},{"arabic":"مصدريّةغير زمانيه","atr":"H.MQZ","color":"#AD2323"},{"arabic":"مصدرية","atr":"H.M","color":"#AD2323"},{"arabic":"مصدريه زمانيه","atr":"H.MZ","color":"#FF5500"},{"arabic":"موطئة للقسم","atr":"H.MQS","color":"#AD2323"},{"arabic":"نا فية للجنس","atr":"H.NJ","color":"#7A57BB"},{"arabic":"ناصبة","atr":"H.NS","color":"#FF5500"},{"arabic":"نافية","atr":"H.NF","color":"#548DD4"},{"arabic":"ناهيّة","atr":"H.NH","color":"#548DD4"},{"arabic":"ندا","atr":"H.ND","color":"#FF5500"},{"arabic":"نفي و استقبال","atr":"H.NFS","color":"#548DD4"},{"arabic":"وصليّة","atr":"H.VO","color":"#FF5500"},{"arabic":"مبهم","atr":"M","color":"#548DD4"},{"arabic":"ضمير متصل غائب منصوبي مجروري","atr":"E.ZTGSJ","color":"#AD2552"},{"arabic":"ضمير متصل متكلم","atr":"E.ZTK","color":"#445706"},{"arabic":"ضمير متصل مخاطب منصوبي مجروري","atr":"E.ZTKHSJ","color":"#AD9765"},{"arabic":"ضمير متصل مرفوعي","atr":"E.ZTGF","color":"#7A57BB"},{"arabic":"الف زينت","atr":"H.NON","color":"#AF2200"},{"arabic":"نون عوض رفع","atr":"H.NON1","color":"#130645"},{"arabic":"تاء تانیث","atr":"H.NON2","color":"#FF5500"},{"arabic":"مقدر","atr":"Z.M","color":"#C5C5C5"}],"TotalCount":77,"Id":"0","IsSuccess":true,"Message":"OK","StatusCode":200,"ValidationMessages":null,"Exception":null,"ResponseTime":"2020-12-02T12:15:30.2174917Z"},"relationName":{"Data":[{"color":"#83ADE0","name":"فاعل","Id":1},{"color":"#445706","name":"مستثنا","Id":2},{"color":"#70869C","name":"خبر","Id":3},{"color":"#70869C","name":"مفعول به","Id":4},{"color":"#D73535","name":"مجرور","Id":5},{"color":"#6F9FDB","name":"مضاف الیه ","Id":6},{"color":"#495706","name":"حال","Id":7},{"color":"#9A3CD9","name":"نعت","Id":8},{"color":"#6F9FDB","name":"بدل","Id":9},{"color":"#4C5706","name":"تمییز","Id":10},{"color":"#7FAAFF","name":"معطوف","Id":11},{"color":"#D8019C","name":"توکید","Id":12},{"color":"#EF7D21","name":"متعلق","Id":13},{"color":"#505706","name":"اسم","Id":14},{"color":"#97881C","name":"صله","Id":15},{"color":"#525706","name":"مفعول معه","Id":16},{"color":"#83ADE0","name":"نائب فاعل","Id":17},{"color":"#AD2323","name":"عطف بیان","Id":18},{"color":"#D8019C","name":"مفعول مطلق","Id":19},{"color":"#D73535","name":"ظرف","Id":20},{"color":"#70869C","name":"شرط","Id":21},{"color":"#7FAAFF","name":"جواب شرط","Id":22},{"color":"#70869C","name":"مفعول له","Id":23},{"color":"#4C5706","name":"منادا","Id":24},{"color":"#83ADE0","name":"جواب امر","Id":25},{"color":"#D8019C","name":"منصوب به نزع خافض","Id":26},{"color":"#4C5706","name":"جواب ندا","Id":27},{"color":"#83ADE0","name":"جواب قسم","Id":28},{"color":"#4C5706","name":"تعریف","Id":29},{"color":"#D8019C","name":"ضمیر فصل","Id":30},{"color":"#D73535","name":"استثنا","Id":31},{"color":"#EF7D21","name":"زائد","Id":32},{"color":"#7FAAFF","name":"مشتغل عنه","Id":33},{"color":"#4C5706","name":"معطوف بر محل","Id":34},{"color":"#97881C","name":"تأکید","Id":35},{"color":"#7FAAFF","name":"تحقیق","Id":36},{"color":"#7FAAFF","name":"استقبال","Id":37},{"color":"#7FAAFF","name":"استفهام","Id":38},{"color":"#70869C","name":"نفی","Id":39},{"color":"#97881C","name":"نهی","Id":40},{"color":"#83ADE0","name":"حصر","Id":41},{"color":"#83ADE0","name":"جر زائد","Id":42},{"color":"#D8019C","name":"ابتدا","Id":43},{"color":"#445706","name":"تنبیه","Id":44},{"color":"#97881C","name":"حرف جواب","Id":45},{"color":"#445706","name":"سکت","Id":46},{"color":"#70869C","name":"طلب","Id":47},{"color":"#D8019C","name":"استیناف","Id":48},{"color":"#D8019C","name":"تحضیض","Id":49},{"color":"#83ADE0","name":"تفسیر","Id":50},{"color":"#70869C","name":"تفصیل","Id":51},{"color":"#D8019C","name":"جواب","Id":52},{"color":"#445706","name":"اعتراض","Id":53},{"color":"#D8019C","name":"موطئه","Id":54},{"color":"#7FAAFF","name":"عطف","Id":55},{"color":"#70869C","name":"مفاجاة","Id":56},{"color":"#7FAAFF","name":"مخففه","Id":57},{"color":"#D73535","name":"معیه","Id":58},{"color":"#445706","name":"مصدریه","Id":59},{"color":"#D8019C","name":"اشباع","Id":60},{"color":"#70869C","name":"حالیه","Id":61},{"color":"#D8019C","name":"وقایه","Id":62},{"color":"#FF2200","name":"الف زینت","Id":63},{"color":"#130645","name":"نون عوض رفع","Id":64},{"color":"#FF5500","name":"تاء تانیث","Id":65}],"TotalCount":65,"Id":"0","IsSuccess":true,"Message":"OK","StatusCode":200,"ValidationMessages":null,"Exception":null,"ResponseTime":"2020-12-02T12:15:30.2174917Z"},"ayeh":{"node":{"Data":[{"atrId":52,"delete":0,"id":99922,"idWord":73414,"nextId":133585,"prevId":null,"Word":"أَمْ","xml":"<word Seq=\"1\" Entry=\"أَمْ\" Affix=\"هسته\" Pos=\"حرف\" Case=\"مبنی بر سکون\" Kol=\"عاطفه\" Slice=\"أَمْ\" />","isNewWord":0},{"atrId":41,"delete":0,"id":99923,"idWord":73415,"nextId":99924,"prevId":133585,"Word":"لَ","xml":"<word Seq=\"1\" Entry=\"لِ\" Affix=\"پیشوند\" Pos=\"حرف\" Case=\"مبنی بر فتح\" Kol=\"جاره\" Slice=\"لَ\" />","isNewWord":0},{"atrId":21,"delete":0,"id":99924,"idWord":73415,"nextId":99925,"prevId":99923,"Word":"هُمْ","xml":"<word Seq=\"2\" Entry=\"هُمْ\" Affix=\"هسته\" Pos=\"اسم\" Case=\"مبنی بر سکون\" Categ=\"تهی\" Def=\"معرفه\" Derv=\"\" DervT=\"ضمیر متصل منصوبی مجروری\" Gend=\"مذکر\" Num=\"جمع\" Root=\"تهی\" RootT=\"تهی\" Temp=\"تهی\" Varied=\"تهی\" Decl=\"\" Slice=\"هُمْ\" />","isNewWord":0},{"atrId":19,"delete":0,"id":99925,"idWord":73416,"nextId":99926,"prevId":99924,"Word":"شُرَكَاءُ","xml":"<word Seq=\"1\" Slice=\"شُرَكَاءُ\" Entry=\"شُرَکَاءُ\" Affix=\"هسته\" Pos=\"اسم\" Case=\"مرفوع\" Categ=\"فَعِلَ یَفْعَلُ\" Def=\"نکره\" Derv=\"\" DervT=\"صفت مشبهه\" Gend=\"مذکر\" Num=\"جمع مکسر\" Root=\"شرک\" RootT=\"سالم\" Temp=\"فُعَلَاءُ\" Varied=\"غیر منصرف\" Decl=\"\" />","isNewWord":0},{"atrId":1,"delete":0,"id":99926,"idWord":73417,"nextId":150818,"prevId":99925,"Word":"شَرَع","xml":"<word Seq=\"1\" Slice=\"شَرَع\" Entry=\"شَرَع\" Affix=\"هسته\" Pos=\"فعل\" Case=\"مبنی بر فتح\" Categ=\"فَعَلَ یَفْعَلُ\" Gend=\"مذکر\" Num=\"جمع\" Root=\"شرع\" RootT=\"سالم\" Temp=\"فَعَلُوا\" Time=\"ماضی\" TOV=\"3\" Trans=\"متعدی\" Voic=\"معلوم\" />","isNewWord":0},{"atrId":41,"delete":0,"id":99927,"idWord":73418,"nextId":99928,"prevId":150819,"Word":"لَ","xml":"<word Seq=\"1\" Entry=\"لِ\" Affix=\"پیشوند\" Pos=\"حرف\" Case=\"مبنی بر فتح\" Kol=\"جاره\" Slice=\"لَ\" />","isNewWord":0},{"atrId":21,"delete":0,"id":99928,"idWord":73418,"nextId":133586,"prevId":99927,"Word":"هُمْ","xml":"<word Seq=\"2\" Entry=\"هُمْ\" Affix=\"هسته\" Pos=\"اسم\" Case=\"مبنی بر سکون\" Categ=\"تهی\" Def=\"معرفه\" Derv=\"\" DervT=\"ضمیر متصل منصوبی مجروری\" Gend=\"مذکر\" Num=\"جمع\" Root=\"تهی\" RootT=\"تهی\" Temp=\"تهی\" Varied=\"تهی\" Decl=\"\" Slice=\"هُمْ\" />","isNewWord":0},{"atrId":41,"delete":0,"id":99929,"idWord":73419,"nextId":99930,"prevId":133586,"Word":"مِنَ","xml":"<word Seq=\"1\" Entry=\"مِنْ\" Affix=\"هسته\" Pos=\"حرف\" Case=\"مبنی بر سکون\" Kol=\"جاره\" Slice=\"مِنَ\" />","isNewWord":0},{"atrId":37,"delete":0,"id":99930,"idWord":73420,"nextId":99931,"prevId":99929,"Word":"ال","xml":"<word Seq=\"1\" Slice=\"ال\" Entry=\"الْ\" Affix=\"پیشوند\" Pos=\"حرف\" Case=\"مبنی بر سکون\" Kol=\"تعریف\" />","isNewWord":0},{"atrId":24,"delete":0,"id":99931,"idWord":73420,"nextId":99932,"prevId":99930,"Word":"دِّینِ","xml":"<word Seq=\"2\" Slice=\"دِّینِ\" Entry=\"دِینِ\" Affix=\"هسته\" Pos=\"اسم\" Case=\"مجرور\" Categ=\"فَعَلَ یَفْعِلُ\" Def=\"معرفه\" Derv=\"\" DervT=\"جامد غیر مصدری\" Gend=\"مذکر\" Num=\"مفرد\" Root=\"دین\" RootT=\"اجوف یائی\" Temp=\"فِعْلِ\" Varied=\"منصرف\" Decl=\"\" />","isNewWord":0},{"atrId":26,"delete":0,"id":99932,"idWord":73421,"nextId":99933,"prevId":99931,"Word":"مَا","xml":"<word Seq=\"1\" Slice=\"مَا\" Entry=\"مَا\" Affix=\"هسته\" Pos=\"اسم\" Case=\"مبنی بر سکون\" Categ=\"تهی\" Def=\"معرفه\" Derv=\"\" DervT=\"اسم موصول\" Gend=\"تهی\" Num=\"مشترک\" Root=\"تهی\" RootT=\"تهی\" Temp=\"تهی\" Varied=\"تهی\" Decl=\"\" />","isNewWord":0},{"atrId":63,"delete":0,"id":99933,"idWord":73422,"nextId":99934,"prevId":99932,"Word":"لَمْ","xml":"<word Seq=\"1\" Entry=\"لَمْ\" Affix=\"هسته\" Pos=\"حرف\" Case=\"مبنی بر سکون\" Kol=\"نافیه\" Slice=\"لَمْ\" />","isNewWord":0},{"atrId":1,"delete":0,"id":99934,"idWord":73423,"nextId":99935,"prevId":99933,"Word":"يَأْذَنْ","xml":"<word Seq=\"1\" Slice=\"يَأْذَنْ\" Entry=\"یَأْذَنْ\" Affix=\"هسته\" Pos=\"فعل\" Case=\"مجزوم\" Categ=\"فَعِلَ یَفْعَلُ\" Gend=\"مذکر\" Num=\"مفرد\" Root=\"ءذن\" RootT=\"مهموز الفاء\" Temp=\"یَفْعَلْ\" Time=\"مضارع ساده\" TOV=\"1\" Trans=\"لازم\" Voic=\"معلوم\" />","isNewWord":0},{"atrId":41,"delete":0,"id":99935,"idWord":73424,"nextId":99936,"prevId":99934,"Word":"بِ","xml":"<word Seq=\"1\" Entry=\"بِ\" Affix=\"پیشوند\" Pos=\"حرف\" Case=\"مبنی بر کسر\" Kol=\"جاره\" Slice=\"بِ\" />","isNewWord":0},{"atrId":21,"delete":0,"id":99936,"idWord":73424,"nextId":99937,"prevId":99935,"Word":"هِ","xml":"<word Seq=\"2\" Entry=\"هِ\" Affix=\"هسته\" Pos=\"اسم\" Case=\"مبنی بر کسر\" Categ=\"تهی\" Def=\"معرفه\" Derv=\"\" DervT=\"ضمیر متصل منصوبی مجروری\" Gend=\"مذکر\" Num=\"مفرد\" Root=\"تهی\" RootT=\"تهی\" Temp=\"تهی\" Varied=\"تهی\" Decl=\"\" Slice=\"هِ\" />","isNewWord":0},{"atrId":12,"delete":0,"id":99937,"idWord":73425,"nextId":99938,"prevId":99936,"Word":"اللَّهُ","xml":"<word Seq=\"1\" Entry=\"اللَّهُ\" Affix=\"هسته\" Pos=\"اسم\" Case=\"مرفوع\" Categ=\"ثلاثی مجرد\" Def=\"معرفه\" DervT=\"جامد غیر مصدری\" Alam=\"آری\" Gend=\"مذکر\" Num=\"مفرد\" Root=\"أله\" RootT=\"مهموز الفاء\" Temp=\"تهی\" Varied=\"منصرف\" Slice=\"اللَّهُ\" />","isNewWord":0},{"atrId":52,"delete":0,"id":99938,"idWord":73426,"nextId":99939,"prevId":99937,"Word":"وَ","xml":"<word Seq=\"1\" Slice=\"وَ\" Entry=\"وَ\" Affix=\"هسته\" Pos=\"حرف\" Lemma=\"وَ\" Case=\"مبنی بر فتح\" Kol=\"عاطفه\" Desc=\"\" />","isNewWord":0},{"atrId":4,"delete":0,"id":99939,"idWord":73427,"nextId":99940,"prevId":99938,"Word":"لَوْ","xml":"<word Seq=\"1\" Entry=\"لَوْ\" Affix=\"هسته\" Pos=\"حرف\" Case=\"مبنی بر سکون\" Kol=\"شرطیه\" Slice=\"لَوْ\" />","isNewWord":0},{"atrId":4,"delete":0,"id":99940,"idWord":73428,"nextId":99941,"prevId":99939,"Word":"لَا","xml":"<word Seq=\"1\" Slice=\"لَا\" Entry=\"لَا\" Affix=\"هسته\" Pos=\"حرف\" Case=\"مبنی بر سکون\" Kol=\"نافیه\" />","isNewWord":0},{"atrId":18,"delete":0,"id":99941,"idWord":73429,"nextId":99942,"prevId":99940,"Word":"كَلِمَةُ","xml":"<word Seq=\"1\" Slice=\"كَلِمَةُ\" Entry=\"کَلِمَةُ\" Affix=\"هسته\" Pos=\"اسم\" Case=\"مرفوع\" Categ=\"تفعیل\" Def=\"اضافه\" DervT=\"جامد غیر مصدری\" Gend=\"مؤنث\" Num=\"مفرد\" Root=\"کلم\" RootT=\"سالم\" Temp=\"فَعِلَةُ\" Varied=\"منصرف\" />","isNewWord":0},{"atrId":37,"delete":0,"id":99942,"idWord":73430,"nextId":99943,"prevId":99941,"Word":"الْ","xml":"<word Seq=\"1\" Slice=\"الْ\" Entry=\"الْ\" Affix=\"پیشوند\" Pos=\"حرف\" Case=\"مبنی بر سکون\" Kol=\"تعریف\" />","isNewWord":0},{"atrId":24,"delete":0,"id":99943,"idWord":73430,"nextId":133587,"prevId":99942,"Word":"فَصْلِ","xml":"<word Seq=\"2\" Slice=\"فَصْلِ\" Entry=\"فَصْلِ\" Affix=\"هسته\" Pos=\"اسم\" Case=\"مجرور\" Categ=\"فَعَلَ یَفْعِلُ\" Def=\"معرفه\" Derv=\"\" DervT=\"مصدر\" Gend=\"مذکر\" Num=\"مفرد\" Root=\"فصل\" RootT=\"سالم\" Temp=\"فَعْلِ\" Varied=\"منصرف\" Decl=\"\" />","isNewWord":0},{"atrId":45,"delete":0,"id":99944,"idWord":73431,"nextId":99945,"prevId":133587,"Word":"لَ","xml":"<word Seq=\"1\" Slice=\"لَ\" Entry=\"لَ\" Affix=\"پیشوند\" Pos=\"حرف\" Case=\"مبنی بر فتح\" Kol=\"جواب\" />","isNewWord":0},{"atrId":3,"delete":0,"id":99945,"idWord":73431,"nextId":133590,"prevId":99944,"Word":"قُضِیَ","xml":"<word Seq=\"2\" Slice=\"قُضِیَ\" Entry=\"قُضِی\" Affix=\"هسته\" Pos=\"فعل\" Case=\"مبنی بر فتح\" Categ=\"فَعَلَ یَفْعِلُ\" Gend=\"مذکر\" Num=\"مفرد\" Root=\"قضی\" RootT=\"ناقص یائی\" Temp=\"فُعِلَ\" Time=\"ماضی\" TOV=\"1\" Trans=\"متعدی\" Voic=\"مجهول\" />","isNewWord":0},{"atrId":23,"delete":0,"id":99946,"idWord":73432,"nextId":99947,"prevId":133590,"Word":"بَیْنَ","xml":"<word Seq=\"1\" Entry=\"بَیْنَ\" Affix=\"هسته\" Pos=\"اسم\" Case=\"منصوب\" Categ=\"تهی\" Def=\"اضافه\" Derv=\"\" DervT=\"ظرف\" Gend=\"مذکر\" Num=\"مفرد\" Root=\"بین\" RootT=\"اجوف یائی\" Temp=\"فَعْلَ\" Varied=\"تهی\" Decl=\"\" Slice=\"بَیْنَ\" />","isNewWord":0},{"atrId":69,"delete":0,"id":99947,"idWord":73432,"nextId":99948,"prevId":99946,"Word":"هُمْ","xml":"<word Seq=\"2\" Entry=\"هُمْ\" Affix=\"پسوند\" Pos=\"اسم\" Case=\"مبنی بر سکون\" Categ=\"تهی\" Def=\"معرفه\" Derv=\"\" DervT=\"ضمیر متصل منصوبی مجروری\" Gend=\"مذکر\" Num=\"جمع\" Root=\"تهی\" RootT=\"تهی\" Temp=\"تهی\" Varied=\"تهی\" Decl=\"\" Slice=\"هُمْ\" />","isNewWord":0},{"atrId":33,"delete":0,"id":99948,"idWord":73433,"nextId":99949,"prevId":99947,"Word":"وَ","xml":"<word Seq=\"1\" Slice=\"وَ\" Entry=\"وَ\" Affix=\"هسته\" Pos=\"حرف\" Lemma=\"وَ\" Case=\"مبنی بر فتح\" Kol=\"استینافیه\" Desc=\"\" />","isNewWord":0},{"atrId":56,"delete":0,"id":99949,"idWord":73434,"nextId":99950,"prevId":99948,"Word":"إِنَّ","xml":"<word Seq=\"1\" Entry=\"إِنَّ\" Affix=\"هسته\" Pos=\"حرف\" Case=\"مبنی بر فتح\" Kol=\"مشبهه بالفعل\" Slice=\"إِنَّ\" />","isNewWord":0},{"atrId":0,"delete":0,"id":99950,"idWord":73435,"nextId":99951,"prevId":99949,"Word":"ال","xml":"<word Seq=\"1\" Slice=\"ال\" Entry=\"الْ\" Affix=\"پیشوند\" Pos=\"حرف\" Case=\"مبنی بر سکون\" Kol=\"تعریف\" />","isNewWord":0},{"atrId":15,"delete":0,"id":99951,"idWord":73435,"nextId":133588,"prevId":99950,"Word":"ظَّالِمِینَ","xml":"<word Seq=\"2\" Slice=\"ظَّالِمِینَ\" Entry=\"ظَالِمِینَ\" Affix=\"هسته\" Pos=\"اسم\" Case=\"منصوب\" Categ=\"فَعَلَ یَفْعِلُ\" Def=\"معرفه\" Derv=\"\" DervT=\"اسم فاعل\" Gend=\"مذکر\" Num=\"جمع\" Root=\"ظلم\" RootT=\"سالم\" Temp=\"فَاعِلِینَ\" Varied=\"منصرف\" Decl=\"\" />","isNewWord":0},{"atrId":41,"delete":0,"id":99952,"idWord":73436,"nextId":99953,"prevId":133588,"Word":"لَ","xml":"<word Seq=\"1\" Entry=\"لِ\" Affix=\"پیشوند\" Pos=\"حرف\" Case=\"مبنی بر فتح\" Kol=\"جاره\" Slice=\"لَ\" />","isNewWord":0},{"atrId":21,"delete":0,"id":99953,"idWord":73436,"nextId":99954,"prevId":99952,"Word":"هُمْ","xml":"<word Seq=\"2\" Entry=\"هُمْ\" Affix=\"هسته\" Pos=\"اسم\" Case=\"مبنی بر سکون\" Categ=\"تهی\" Def=\"معرفه\" Derv=\"\" DervT=\"ضمیر متصل منصوبی مجروری\" Gend=\"مذکر\" Num=\"جمع\" Root=\"تهی\" RootT=\"تهی\" Temp=\"تهی\" Varied=\"تهی\" Decl=\"\" Slice=\"هُمْ\" />","isNewWord":0},{"atrId":4,"delete":0,"id":99954,"idWord":73437,"nextId":99955,"prevId":99953,"Word":"عَذَابٌ","xml":"<word Seq=\"1\" Slice=\"عَذَابٌ\" Entry=\"عَذَابٌ\" Affix=\"هسته\" Pos=\"اسم\" Case=\"مرفوع\" Categ=\"تفعیل\" Def=\"نکره\" Derv=\"\" DervT=\"جامد غیر مصدری\" Gend=\"مذکر\" Num=\"مفرد\" Root=\"عذب\" RootT=\"سالم\" Temp=\"فَعَالٌ\" Varied=\"منصرف\" Decl=\"\" />","isNewWord":0},{"atrId":19,"delete":0,"id":99955,"idWord":73438,"nextId":null,"prevId":99954,"Word":"أَلِيمٌ","xml":"<word Seq=\"1\" Slice=\"أَلِيمٌ\" Entry=\"أَلِیمٌ\" Affix=\"هسته\" Pos=\"اسم\" Case=\"مرفوع\" Categ=\"فَعِلَ یَفْعَلُ\" Def=\"نکره\" Derv=\"\" DervT=\"صفت مشبهه\" Gend=\"مذکر\" Num=\"مفرد\" Root=\"ءلم\" RootT=\"مهموز الفاء\" Temp=\"فَعِیلٌ\" Varied=\"منصرف\" Decl=\"\" />","isNewWord":0},{"atrId":76,"delete":0,"id":133585,"idWord":100743,"nextId":99923,"prevId":99922,"Word":"*","xml":null,"isNewWord":1},{"atrId":76,"delete":0,"id":133586,"idWord":100744,"nextId":99929,"prevId":99928,"Word":"*","xml":null,"isNewWord":1},{"atrId":76,"delete":0,"id":133587,"idWord":100745,"nextId":99944,"prevId":99943,"Word":"*","xml":null,"isNewWord":1},{"atrId":76,"delete":0,"id":133588,"idWord":100746,"nextId":99952,"prevId":99951,"Word":"*","xml":null,"isNewWord":1},{"atrId":76,"delete":0,"id":133590,"idWord":100748,"nextId":99946,"prevId":99945,"Word":"هو","xml":null,"isNewWord":1},{"atrId":72,"delete":0,"id":150818,"idWord":73417,"nextId":150819,"prevId":99926,"Word":"ُو","xml":"<word Seq=\"2\" Slice=\"ُو\" Entry=\"ُو\" Affix=\"پسوند\" Pos=\"اسم\" Case=\"مبنی بر سکون\" Categ=\"تهی\" Def=\"معرفه\" Derv=\"\" DervT=\"ضمیر متصل مرفوعی\" Gend=\"مذکر\" Num=\"جمع\" Root=\"تهی\" RootT=\"تهی\" Temp=\"تهی\" Varied=\"تهی\" Decl=\"\" />","isNewWord":0},{"atrId":73,"delete":0,"id":150819,"idWord":73417,"nextId":99927,"prevId":150818,"Word":"ا","xml":"<word Seq=\"3\" Slice=\"ا\" Entry=\"ا\" Affix=\"پسوند\" Pos=\"حرف\" Case=\"مبنی بر سکون\" Kol=\"الف زینت\" />","isNewWord":0}],"TotalCount":41,"Id":"0","IsSuccess":true,"Message":"OK","StatusCode":200,"ValidationMessages":null,"Exception":null,"ResponseTime":"2020-12-02T12:15:30.2174917Z"},"edge":{"Data":[{"arrow":"LTR","ayehId":21,"from":99924,"to":99923,"id":118527,"relationId":5,"word1":"هُمْ","word2":"لَ","idRun":99924},{"arrow":"LTR","ayehId":21,"from":99925,"to":99922,"id":165557,"relationId":55,"word1":"شُرَكَاءُ","word2":"أَمْ","idRun":99925},{"arrow":"LTR","ayehId":21,"from":99926,"to":99925,"id":118529,"relationId":8,"word1":"شَرَع","word2":"شُرَكَاءُ","idRun":99926},{"arrow":"LTR","ayehId":21,"from":99927,"to":99926,"id":118530,"relationId":13,"word1":"لَ","word2":"شَرَع","idRun":99927},{"arrow":"LTR","ayehId":21,"from":99928,"to":99927,"id":118531,"relationId":5,"word1":"هُمْ","word2":"لَ","idRun":99928},{"arrow":"LTR","ayehId":21,"from":99931,"to":99929,"id":118532,"relationId":5,"word1":"دِّینِ","word2":"مِنَ","idRun":99931},{"arrow":"RTL","ayehId":21,"from":99931,"to":99930,"id":51162,"relationId":29,"word1":"دِّینِ","word2":"ال","idRun":99931},{"arrow":"LTR","ayehId":21,"from":99932,"to":99926,"id":118535,"relationId":4,"word1":"مَا","word2":"شَرَع","idRun":99932},{"arrow":"LTR","ayehId":21,"from":99933,"to":99932,"id":165536,"relationId":15,"word1":"لَمْ","word2":"مَا","idRun":99933},{"arrow":"LTR","ayehId":21,"from":99934,"to":99933,"id":165537,"relationId":39,"word1":"يَأْذَنْ","word2":"لَمْ","idRun":99934},{"arrow":"LTR","ayehId":21,"from":99935,"to":99934,"id":118537,"relationId":13,"word1":"بِ","word2":"يَأْذَنْ","idRun":99935},{"arrow":"LTR","ayehId":21,"from":99936,"to":99935,"id":118538,"relationId":5,"word1":"هِ","word2":"بِ","idRun":99936},{"arrow":"LTR","ayehId":21,"from":99937,"to":99934,"id":118539,"relationId":1,"word1":"اللَّهُ","word2":"يَأْذَنْ","idRun":99937},{"arrow":"LTR","ayehId":21,"from":99938,"to":99926,"id":165559,"relationId":34,"word1":"وَ","word2":"شَرَع","idRun":99938},{"arrow":"LTR","ayehId":21,"from":99939,"to":99938,"id":165558,"relationId":55,"word1":"لَوْ","word2":"وَ","idRun":99939},{"arrow":"LTR","ayehId":21,"from":99941,"to":99939,"id":165560,"relationId":21,"word1":"كَلِمَةُ","word2":"لَوْ","idRun":99941},{"arrow":"LTR","ayehId":21,"from":99943,"to":99941,"id":118540,"relationId":6,"word1":"فَصْلِ","word2":"كَلِمَةُ","idRun":99943},{"arrow":"RTL","ayehId":21,"from":99943,"to":99942,"id":51161,"relationId":29,"word1":"فَصْلِ","word2":"الْ","idRun":99943},{"arrow":"LTR","ayehId":21,"from":99944,"to":99939,"id":165561,"relationId":22,"word1":"لَ","word2":"لَوْ","idRun":99944},{"arrow":"LTR","ayehId":21,"from":99945,"to":99944,"id":165562,"relationId":52,"word1":"قُضِیَ","word2":"لَ","idRun":99945},{"arrow":"LTR","ayehId":21,"from":99946,"to":99945,"id":118567,"relationId":20,"word1":"بَیْنَ","word2":"قُضِیَ","idRun":99946},{"arrow":"LTR","ayehId":21,"from":99947,"to":99946,"id":118543,"relationId":6,"word1":"هُمْ","word2":"بَیْنَ","idRun":99947},{"arrow":"LTR","ayehId":21,"from":99949,"to":99948,"id":165563,"relationId":48,"word1":"إِنَّ","word2":"وَ","idRun":99949},{"arrow":"LTR","ayehId":21,"from":99951,"to":99949,"id":118545,"relationId":14,"word1":"ظَّالِمِینَ","word2":"إِنَّ","idRun":99951},{"arrow":"RTL","ayehId":21,"from":99951,"to":99950,"id":48429,"relationId":29,"word1":"ظَّالِمِینَ","word2":"ال","idRun":99951},{"arrow":"LTR","ayehId":21,"from":99953,"to":99952,"id":118547,"relationId":5,"word1":"هُمْ","word2":"لَ","idRun":99953},{"arrow":"LTR","ayehId":21,"from":99954,"to":99949,"id":118554,"relationId":3,"word1":"عَذَابٌ","word2":"إِنَّ","idRun":99954},{"arrow":"LTR","ayehId":21,"from":99955,"to":99954,"id":118550,"relationId":8,"word1":"أَلِيمٌ","word2":"عَذَابٌ","idRun":99955},{"arrow":"LTR","ayehId":21,"from":133585,"to":99923,"id":118526,"relationId":13,"word1":"*","word2":"لَ","idRun":133585},{"arrow":"RTL","ayehId":21,"from":133585,"to":99925,"id":118528,"relationId":3,"word1":"*","word2":"شُرَكَاءُ","idRun":133585},{"arrow":"LTR","ayehId":21,"from":133586,"to":99929,"id":118533,"relationId":13,"word1":"*","word2":"مِنَ","idRun":133586},{"arrow":"RTL","ayehId":21,"from":133586,"to":99932,"id":118534,"relationId":7,"word1":"*","word2":"مَا","idRun":133586},{"arrow":"LTR","ayehId":21,"from":133587,"to":99941,"id":118541,"relationId":3,"word1":"*","word2":"كَلِمَةُ","idRun":133587},{"arrow":"LTR","ayehId":21,"from":133588,"to":99952,"id":118546,"relationId":13,"word1":"*","word2":"لَ","idRun":133588},{"arrow":"RTL","ayehId":21,"from":133588,"to":99954,"id":118549,"relationId":3,"word1":"*","word2":"عَذَابٌ","idRun":133588},{"arrow":"LTR","ayehId":21,"from":133590,"to":99945,"id":118571,"relationId":17,"word1":"هو","word2":"قُضِیَ","idRun":133590},{"arrow":"LTR","ayehId":21,"from":150818,"to":99926,"id":235759,"relationId":1,"word1":"ُو","word2":"شَرَع","idRun":150818},{"arrow":"LTR","ayehId":21,"from":150819,"to":99926,"id":209605,"relationId":63,"word1":"ا","word2":"شَرَع","idRun":150819}],"TotalCount":38,"Id":"0","IsSuccess":true,"Message":"OK","StatusCode":200,"ValidationMessages":null,"Exception":null,"ResponseTime":"2020-12-02T12:15:30.2174917Z"},"text":[{"Id":4333,"Number":21,"HasProstration":false,"PageNumber":485,"JuzNumber":25,"Text":"أَمۡ لَهُمۡ شُرَكَـٰٓؤُاْ شَرَعُواْ لَهُم مِّنَ ٱلدِّينِ مَا لَمۡ يَأۡذَنۢ بِهِ ٱللَّهُ<em class=\"sajavandi-sign\">ۚ</em> وَلَوۡلَا كَلِمَةُ ٱلۡفَصۡلِ لَقُضِيَ بَيۡنَهُمۡ<em class=\"sajavandi-sign\">ۗ</em> وَإِنَّ ٱلظَّـٰلِمِينَ لَهُمۡ عَذَابٌ أَلِيمٞ","SurahTitle":"الشورى","SurahId":42,"FileUrl":"/File/Sound/Recitation/1-AbdeAlrahmaanSudis/sudis042021.mp3","MaxAyahNumber":53,"MaxAyahNumberPrevSurah":54,"ResultCount":1}]}},"Id":null,"IsSuccess":true,"Message":null,"StatusCode":200,"ValidationMessages":null,"Exception":null,"ResponseTime":"2020-12-02T12:15:30.1779208Z"}